setup.py
jobid/__init__.py
jobid/jobid.py
jobid.egg-info/PKG-INFO
jobid.egg-info/SOURCES.txt
jobid.egg-info/dependency_links.txt
jobid.egg-info/not-zip-safe
jobid.egg-info/top_level.txt