Metadata-Version: 1.0
Name: jobid
Version: 0.3.0
Summary: A python JOBID number generator
Home-page: https://github.com/deparkes/jobid
Author: deparkes
Author-email: deparkes@gmail.com
License: GPL
Platform: UNKNOWN
